turtle_canon/__init__.py
turtle_canon/canon.py
turtle_canon/cli/__init__.py
turtle_canon/cli/cmd_turtle_canon.py
turtle_canon/cli/utils.py
turtle_canon/utils/__init__.py
turtle_canon/utils/exceptions.py
turtle_canon/utils/warnings.py
turtle_canon-0.1.1.dist-info/METADATA
turtle_canon-0.1.1.dist-info/WHEEL
turtle_canon-0.1.1.dist-info/entry_points.txt
turtle_canon-0.1.1.dist-info/licenses/LICENSE
turtle_canon-0.1.1.dist-info/RECORD
