Metadata-Version: 2.4
Name: turtle-canon
Version: 0.1.1
Summary: A tool for canonizing Turtle (`.ttl`) ontology files.
Project-URL: Home, https://CasperWA.github.io/turtle-canon
Project-URL: Documentation, https://CasperWA.github.io/turtle-canon
Project-URL: Source, https://github.com/CasperWA/turtle-canon
Project-URL: Issue Tracker, https://github.com/CasperWA/turtle-canon/issues
Project-URL: Changelog, https://github.com/CasperWA/turtle-canon/blob/main/CHANGELOG.md
Project-URL: Package, https://pypi.org/project/turtle-canon
Author-email: Casper Welzel Andersen <casper.w.andersen@sintef.no>
Maintainer-email: Casper Welzel Andersen <casper.w.andersen@sintef.no>, "Tor S. Haugland" <tor.haugland@sintef.no>
License: MIT License
License-File: LICENSE
Keywords: ontology,turtle
Classifier: Development Status :: 2 - Pre-Alpha
Classifier: Environment :: Console
Classifier: Intended Audience :: Developers
Classifier: Intended Audience :: Science/Research
Classifier: License :: OSI Approved :: MIT License
Classifier: Natural Language :: English
Classifier: Programming Language :: Python :: 3 :: Only
Classifier: Programming Language :: Python :: 3.10
Classifier: Programming Language :: Python :: 3.11
Classifier: Programming Language :: Python :: 3.12
Classifier: Programming Language :: Python :: 3.13
Classifier: Topic :: Software Development
Classifier: Topic :: Software Development :: Pre-processors
Classifier: Topic :: Software Development :: Testing
Classifier: Topic :: Software Development :: Version Control
Classifier: Topic :: Text Processing
Classifier: Topic :: Utilities
Requires-Python: ~=3.10
Requires-Dist: rdflib<8,>=6.0.1
Provides-Extra: dev
Requires-Dist: mike~=2.0; extra == 'dev'
Requires-Dist: mkdocs-awesome-pages-plugin~=2.9; extra == 'dev'
Requires-Dist: mkdocs-material~=9.5; extra == 'dev'
Requires-Dist: mkdocs-minify-plugin~=0.8.0; extra == 'dev'
Requires-Dist: mkdocstrings[python]~=0.28.0; extra == 'dev'
Requires-Dist: mkdocs~=1.5; extra == 'dev'
Requires-Dist: pre-commit~=4.0; extra == 'dev'
Requires-Dist: pytest-cov~=6.0; extra == 'dev'
Requires-Dist: pytest~=8.0; extra == 'dev'
Provides-Extra: docs
Requires-Dist: mike~=2.0; extra == 'docs'
Requires-Dist: mkdocs-awesome-pages-plugin~=2.9; extra == 'docs'
Requires-Dist: mkdocs-material~=9.5; extra == 'docs'
Requires-Dist: mkdocs-minify-plugin~=0.8.0; extra == 'docs'
Requires-Dist: mkdocstrings[python]~=0.28.0; extra == 'docs'
Requires-Dist: mkdocs~=1.5; extra == 'docs'
